package b.k.a;

import android.content.Context;
import android.os.Environment;
import android.util.Log;
import java.io.Closeable;
import java.io.File;
import java.io.IOException;

public class a
{
  public a(Context paramContext) {}
  
  private void a(Closeable paramCloseable)
  {
    if (paramCloseable != null) {
      try
      {
        paramCloseable.close();
        return;
      }
      catch (IOException paramCloseable) {}
    }
  }
  
  public String a()
  {
    return Environment.getExternalStorageDirectory().getAbsolutePath();
  }
  
  public boolean a(String paramString)
  {
    Object localObject = new File(paramString);
    if (((File)localObject).exists())
    {
      localObject = new StringBuilder();
      ((StringBuilder)localObject).append("Directory '");
      ((StringBuilder)localObject).append(paramString);
      ((StringBuilder)localObject).append("' already exists");
      Log.w("Storage", ((StringBuilder)localObject).toString());
      return false;
    }
    return ((File)localObject).mkdirs();
  }
  
  /* Error */
  public boolean a(String paramString1, String paramString2)
  {
    // Byte code:
    //   0: aload_0
    //   1: aload_1
    //   2: invokevirtual 71	b/k/a/a:c	(Ljava/lang/String;)Ljava/io/File;
    //   5: astore 6
    //   7: aload 6
    //   9: invokevirtual 74	java/io/File:isFile	()Z
    //   12: ifne +5 -> 17
    //   15: iconst_0
    //   16: ireturn
    //   17: aconst_null
    //   18: astore 4
    //   20: aconst_null
    //   21: astore_1
    //   22: aconst_null
    //   23: astore 8
    //   25: aconst_null
    //   26: astore 7
    //   28: aload 7
    //   30: astore_3
    //   31: aload 8
    //   33: astore 5
    //   35: new 76	java/io/FileInputStream
    //   38: dup
    //   39: aload 6
    //   41: invokespecial 79	java/io/FileInputStream:<init>	(Ljava/io/File;)V
    //   44: astore 6
    //   46: aload 6
    //   48: astore_1
    //   49: aload 7
    //   51: astore_3
    //   52: aload 6
    //   54: astore 4
    //   56: aload 8
    //   58: astore 5
    //   60: new 81	java/io/FileOutputStream
    //   63: dup
    //   64: new 28	java/io/File
    //   67: dup
    //   68: aload_2
    //   69: invokespecial 35	java/io/File:<init>	(Ljava/lang/String;)V
    //   72: invokespecial 82	java/io/FileOutputStream:<init>	(Ljava/io/File;)V
    //   75: astore_2
    //   76: aload 6
    //   78: astore_1
    //   79: aload_2
    //   80: astore_3
    //   81: aload 6
    //   83: astore 4
    //   85: aload_2
    //   86: astore 5
    //   88: aload 6
    //   90: invokevirtual 86	java/io/FileInputStream:getChannel	()Ljava/nio/channels/FileChannel;
    //   93: astore 7
    //   95: aload 6
    //   97: astore_1
    //   98: aload_2
    //   99: astore_3
    //   100: aload 6
    //   102: astore 4
    //   104: aload_2
    //   105: astore 5
    //   107: aload_2
    //   108: invokevirtual 87	java/io/FileOutputStream:getChannel	()Ljava/nio/channels/FileChannel;
    //   111: astore 8
    //   113: aload 6
    //   115: astore_1
    //   116: aload_2
    //   117: astore_3
    //   118: aload 6
    //   120: astore 4
    //   122: aload_2
    //   123: astore 5
    //   125: aload 7
    //   127: lconst_0
    //   128: aload 7
    //   130: invokevirtual 93	java/nio/channels/FileChannel:size	()J
    //   133: aload 8
    //   135: invokevirtual 97	java/nio/channels/FileChannel:transferTo	(JJLjava/nio/channels/WritableByteChannel;)J
    //   138: pop2
    //   139: aload_0
    //   140: aload 6
    //   142: invokespecial 99	b/k/a/a:a	(Ljava/io/Closeable;)V
    //   145: aload_0
    //   146: aload_2
    //   147: invokespecial 99	b/k/a/a:a	(Ljava/io/Closeable;)V
    //   150: iconst_1
    //   151: ireturn
    //   152: astore_2
    //   153: goto +33 -> 186
    //   156: astore_2
    //   157: aload 4
    //   159: astore_1
    //   160: aload 5
    //   162: astore_3
    //   163: ldc 52
    //   165: ldc 101
    //   167: aload_2
    //   168: invokestatic 105	android/util/Log:e	(Ljava/lang/String;Ljava/lang/String;Ljava/lang/Throwable;)I
    //   171: pop
    //   172: aload_0
    //   173: aload 4
    //   175: invokespecial 99	b/k/a/a:a	(Ljava/io/Closeable;)V
    //   178: aload_0
    //   179: aload 5
    //   181: invokespecial 99	b/k/a/a:a	(Ljava/io/Closeable;)V
    //   184: iconst_0
    //   185: ireturn
    //   186: aload_0
    //   187: aload_1
    //   188: invokespecial 99	b/k/a/a:a	(Ljava/io/Closeable;)V
    //   191: aload_0
    //   192: aload_3
    //   193: invokespecial 99	b/k/a/a:a	(Ljava/io/Closeable;)V
    //   196: aload_2
    //   197: athrow
    // Local variable table:
    //   start	length	slot	name	signature
    //   0	198	0	this	a
    //   0	198	1	paramString1	String
    //   0	198	2	paramString2	String
    //   30	163	3	localObject1	Object
    //   18	156	4	localObject2	Object
    //   33	147	5	localObject3	Object
    //   5	136	6	localObject4	Object
    //   26	103	7	localFileChannel1	java.nio.channels.FileChannel
    //   23	111	8	localFileChannel2	java.nio.channels.FileChannel
    // Exception table:
    //   from	to	target	type
    //   35	46	152	finally
    //   60	76	152	finally
    //   88	95	152	finally
    //   107	113	152	finally
    //   125	139	152	finally
    //   163	172	152	finally
    //   35	46	156	java/lang/Exception
    //   60	76	156	java/lang/Exception
    //   88	95	156	java/lang/Exception
    //   107	113	156	java/lang/Exception
    //   125	139	156	java/lang/Exception
  }
  
  public boolean b(String paramString)
  {
    return new File(paramString).delete();
  }
  
  public File c(String paramString)
  {
    return new File(paramString);
  }
}
